xlrd/__init__.py
xlrd/biffh.py
xlrd/book.py
xlrd/compdoc.py
xlrd/formatting.py
xlrd/formula.py
xlrd/info.py
xlrd/sheet.py
xlrd/timemachine.py
xlrd/xldate.py
xlrd-2.0.0.data/scripts/runxlrd.py
xlrd-2.0.0.dist-info/LICENSE
xlrd-2.0.0.dist-info/METADATA
xlrd-2.0.0.dist-info/WHEEL
xlrd-2.0.0.dist-info/top_level.txt
xlrd-2.0.0.dist-info/RECORD
