Metadata-Version: 2.1
Name: xlrd
Version: 2.0.0
Summary: Library for developers to extract data from Microsoft Excel (tm) .xls spreadsheet files
Home-page: http://www.python-excel.org/
Author: Chris Withers
Author-email: chris@withers.org
License: BSD
Keywords: xls,excel,spreadsheet,workbook
Platform: UNKNOWN
Classifier: Development Status :: 5 - Production/Stable
Classifier: Intended Audience :: Developers
Classifier: License :: OSI Approved :: BSD License
Classifier: Programming Language :: Python
Classifier: Programming Language :: Python :: 2
Classifier: Programming Language :: Python :: 2.7
Classifier: Programming Language :: Python :: 3
Classifier: Programming Language :: Python :: 3.6
Classifier: Programming Language :: Python :: 3.7
Classifier: Programming Language :: Python :: 3.8
Classifier: Programming Language :: Python :: 3.9
Classifier: Operating System :: OS Independent
Classifier: Topic :: Database
Classifier: Topic :: Office/Business
Classifier: Topic :: Software Development :: Libraries :: Python Modules
Requires-Python: >=2.7, !=3.0.*, !=3.1.*, !=3.2.*, !=3.3.*, !=3.4.*, !=3.5.*
Provides-Extra: test
Provides-Extra: docs
Provides-Extra: build
